mbrl/__init__.py
mbrl/constants.py
mbrl/types.py
mbrl/algorithms/__init__.py
mbrl/algorithms/mbpo.py
mbrl/algorithms/pets.py
mbrl/algorithms/planet.py
mbrl/diagnostics/__init__.py
mbrl/diagnostics/control_env.py
mbrl/diagnostics/eval_model_on_dataset.py
mbrl/diagnostics/finetune_model_with_controller.py
mbrl/diagnostics/planet_visualizer.py
mbrl/diagnostics/training_browser.py
mbrl/diagnostics/visualize_model_preds.py
mbrl/env/__init__.py
mbrl/env/ant_truncated_obs.py
mbrl/env/cartpole_continuous.py
mbrl/env/humanoid_truncated_obs.py
mbrl/env/mujoco_envs.py
mbrl/env/mujoco_pixel_wrapper.py
mbrl/env/pets_cartpole.py
mbrl/env/pets_halfcheetah.py
mbrl/env/pets_pusher.py
mbrl/env/pets_reacher.py
mbrl/env/reward_fns.py
mbrl/env/termination_fns.py
mbrl/examples/conf/main.yaml
mbrl/examples/conf/algorithm/mbpo.yaml
mbrl/examples/conf/algorithm/pets.yaml
mbrl/examples/conf/algorithm/planet.yaml
mbrl/examples/conf/dynamics_model/basic_ensemble.yaml
mbrl/examples/conf/dynamics_model/gaussian_mlp.yaml
mbrl/examples/conf/dynamics_model/gaussian_mlp_ensemble.yaml
mbrl/examples/conf/dynamics_model/planet.yaml
mbrl/examples/conf/overrides/mbpo_ant.yaml
mbrl/examples/conf/overrides/mbpo_cartpole.yaml
mbrl/examples/conf/overrides/mbpo_halfcheetah.yaml
mbrl/examples/conf/overrides/mbpo_hopper.yaml
mbrl/examples/conf/overrides/mbpo_humanoid.yaml
mbrl/examples/conf/overrides/mbpo_inv_pendulum.yaml
mbrl/examples/conf/overrides/mbpo_pusher.yaml
mbrl/examples/conf/overrides/mbpo_walker.yaml
mbrl/examples/conf/overrides/pb_mbpo_inv_pendulum.yaml
mbrl/examples/conf/overrides/pets_cartpole.yaml
mbrl/examples/conf/overrides/pets_cartpole_paper_version.yaml
mbrl/examples/conf/overrides/pets_halfcheetah.yaml
mbrl/examples/conf/overrides/pets_hopper.yaml
mbrl/examples/conf/overrides/pets_icem_cartpole.yaml
mbrl/examples/conf/overrides/pets_inv_pendulum.yaml
mbrl/examples/conf/overrides/pets_mppi_halfcheetah.yaml
mbrl/examples/conf/overrides/pets_pusher.yaml
mbrl-0.2.0.dist-info/LICENSE
mbrl-0.2.0.dist-info/METADATA
mbrl-0.2.0.dist-info/WHEEL
mbrl-0.2.0.dist-info/top_level.txt
mbrl-0.2.0.dist-info/RECORD
