Metadata-Version: 2.1
Name: mbrl
Version: 0.2.0
Summary: A PyTorch library for model-based reinforcement learning research
Home-page: https://github.com/facebookresearch/mbrl-lib
Author: Facebook AI Research
Classifier: License :: OSI Approved :: MIT License
Classifier: Programming Language :: Python :: 3
Classifier: Programming Language :: Python :: 3.8
Classifier: Programming Language :: Python :: 3.9
Classifier: Programming Language :: Python :: 3.10
Classifier: Intended Audience :: Science/Research
Classifier: Topic :: Scientific/Engineering :: Artificial Intelligence
Requires-Python: >=3.8
License-File: LICENSE
Requires-Dist: omegaconf (<2.1,>=2.0)
Requires-Dist: hydra-core (==1.0.3)
Requires-Dist: termcolor (>=1.1.0)
Requires-Dist: tensorboard (>=2.4.0)
Requires-Dist: imageio (>=2.9.0)
Requires-Dist: numpy (>=1.19.1)
Requires-Dist: matplotlib (>=3.3.1)
Requires-Dist: gymnasium (==0.26.3)
Requires-Dist: jupyter (>=1.0.0)
Requires-Dist: pytest (>=6.0.1)
Requires-Dist: sk-video (>=1.1.10)
Requires-Dist: tqdm (>=4.48.2)
Provides-Extra: dev
Requires-Dist: omegaconf (<2.1,>=2.0) ; extra == 'dev'
Requires-Dist: hydra-core (==1.0.3) ; extra == 'dev'
Requires-Dist: termcolor (>=1.1.0) ; extra == 'dev'
Requires-Dist: tensorboard (>=2.4.0) ; extra == 'dev'
Requires-Dist: imageio (>=2.9.0) ; extra == 'dev'
Requires-Dist: numpy (>=1.19.1) ; extra == 'dev'
Requires-Dist: matplotlib (>=3.3.1) ; extra == 'dev'
Requires-Dist: gymnasium (==0.26.3) ; extra == 'dev'
Requires-Dist: jupyter (>=1.0.0) ; extra == 'dev'
Requires-Dist: pytest (>=6.0.1) ; extra == 'dev'
Requires-Dist: sk-video (>=1.1.10) ; extra == 'dev'
Requires-Dist: tqdm (>=4.48.2) ; extra == 'dev'
Requires-Dist: sphinx (>=3.3.1) ; extra == 'dev'
Requires-Dist: nbsphinx (>=0.8.0) ; extra == 'dev'
Requires-Dist: sphinx-rtd-theme (>=0.5.0) ; extra == 'dev'
Requires-Dist: flake8 (>=3.9.2) ; extra == 'dev'
Requires-Dist: mypy (>=0.991) ; extra == 'dev'
Requires-Dist: black (>=23.1.0) ; extra == 'dev'
Requires-Dist: importlib-metadata (<5) ; extra == 'dev'
Requires-Dist: types-pyyaml (>=0.1.6) ; extra == 'dev'
Requires-Dist: types-termcolor (>=0.1.0) ; extra == 'dev'
Requires-Dist: pre-commit (>=2.7.1) ; extra == 'dev'
